gitbackhub/__init__.py
gitbackhub/cli.py
gitbackhub-0.2.0.dist-info/LICENSE
gitbackhub-0.2.0.dist-info/METADATA
gitbackhub-0.2.0.dist-info/WHEEL
gitbackhub-0.2.0.dist-info/entry_points.txt
gitbackhub-0.2.0.dist-info/top_level.txt
gitbackhub-0.2.0.dist-info/RECORD
