Metadata-Version: 2.1
Name: gitbackhub
Version: 0.2.0
Summary: A script to backup / mirror GitHub repositories.
Home-page: https://github.com/MarkusH/gitbackhub
Author: Markus Holtermann
Author-email: info@markusholtermann.eu
License: MIT
Platform: UNKNOWN
Classifier: Development Status :: 5 - Production/Stable
Classifier: Environment :: Console
Classifier: Intended Audience :: Developers
Classifier: Intended Audience :: End Users/Desktop
Classifier: License :: OSI Approved :: MIT License
Classifier: Operating System :: POSIX :: Linux
Classifier: Programming Language :: Python :: 3.6
Classifier: Topic :: Software Development :: Version Control
Classifier: Topic :: System :: Archiving :: Backup
Classifier: Topic :: Utilities
Requires-Dist: Click (>=6)
Requires-Dist: requests (>=2.18.3)
Provides-Extra: testing
Requires-Dist: pytest (<5.4,>=5.3) ; extra == 'testing'
